README.md
setup.py
Django_GSheets_Export.egg-info/PKG-INFO
Django_GSheets_Export.egg-info/SOURCES.txt
Django_GSheets_Export.egg-info/dependency_links.txt
Django_GSheets_Export.egg-info/requires.txt
Django_GSheets_Export.egg-info/top_level.txt
gsheets/__init__.py
gsheets/gsheets.py