Metadata-Version: 2.1
Name: Django-GSheets-Export
Version: 0.2
Summary: Export data from Django tp Google Sheets
Home-page: http://your-package-url.com/
Author: Nicolas Candela
Author-email: nico.candela@gmail.com
License: MIT License
Classifier: Environment :: Web Environment
Classifier: Framework :: Django
Requires-Dist: Django>=4.1
Requires-Dist: django-environ==0.11.2
Requires-Dist: google-api-python-client
Requires-Dist: google-auth
